<?xml version="1.0" encoding="UTF-8" ?>
<?qbxml version="13.0" ?>
<!-- WARNING!!!: This file is generated by QuickBooksPhpDevKit\QBXML\Schema\Generator using the /data/qbxmlops130.xml file in this package. -->
<QBXML>
<QBXMLMsgsRq onError="stopOnErrror">
<CompanyActivityQueryRq>
<!-- not in QBOE, v2.0 -->
<IncludeRetElement>STRTYPE</IncludeRetElement> <!-- optional, may repeat -->
</CompanyActivityQueryRq>
</QBXMLMsgsRq>
<QBXMLMsgsRs onError="stopOnErrror">
<CompanyActivityQueryRs statusCode="INTTYPE" statusSeverity="STRTYPE" statusMessage="STRTYPE">
<!-- not in QBOE, v2.0 -->
<CompanyActivityRet> <!-- optional -->
<LastRestoreTime>DATETIMETYPE</LastRestoreTime> <!-- required -->
<LastCondenseTime>DATETIMETYPE</LastCondenseTime> <!-- required -->
<!-- v3.0 -->
</CompanyActivityRet>
</CompanyActivityQueryRs>
</QBXMLMsgsRs>
</QBXML>
